pycounts_cl/__init__.py
pycounts_cl/plotting.py
pycounts_cl/pycounts_cl.py
pycounts_cl-0.1.1.dist-info/LICENSE
pycounts_cl-0.1.1.dist-info/METADATA
pycounts_cl-0.1.1.dist-info/WHEEL
pycounts_cl-0.1.1.dist-info/RECORD
