Metadata-Version: 2.1
Name: pycounts_cl
Version: 0.1.1
Summary: 524 Assignment 1
License: MIT
Author: Chun Li
Requires-Python: >=3.9,<4.0
Classifier: License :: OSI Approved :: MIT License
Classifier: Programming Language :: Python :: 3
Classifier: Programming Language :: Python :: 3.9
Classifier: Programming Language :: Python :: 3.10
Classifier: Programming Language :: Python :: 3.11
Classifier: Programming Language :: Python :: 3.12
Requires-Dist: matplotlib (>=3.8.2,<4.0.0)
Requires-Dist: numpy (==1.21.5) ; python_version >= "3.7" and python_version < "3.11"
